shinerainsevenlib/__init__.py
shinerainsevenlib/standard.py
shinerainsevenlib/core/__init__.py
shinerainsevenlib/core/m0_text_io.py
shinerainsevenlib/core/m1_core_util.py
shinerainsevenlib/core/m2_core_data_structures.py
shinerainsevenlib/core/m3_core_nonpure.py
shinerainsevenlib/core/m4_core_ui.py
shinerainsevenlib/core/m5_batch_util.py
shinerainsevenlib/core/m6_jslike.py
shinerainsevenlib/files/__init__.py
shinerainsevenlib/files/m0_files_wrappers.py
shinerainsevenlib/files/m1_files_listing.py
shinerainsevenlib/files/m2_files_higher.py
shinerainsevenlib-1.1.0.dist-info/licenses/LICENSE
shinerainsevenlib-1.1.0.dist-info/METADATA
shinerainsevenlib-1.1.0.dist-info/WHEEL
shinerainsevenlib-1.1.0.dist-info/top_level.txt
shinerainsevenlib-1.1.0.dist-info/RECORD
