Metadata-Version: 2.4
Name: shinerainsevenlib
Version: 1.1.0
Summary: Useful unadorned utilities for powerful Python programming
Author-email: Ben Fisher <shinerainseven@gmail.com>
License-Expression: LGPL-2.1-or-later
Project-URL: Homepage, https://github.com/moltenform/shinerainsevenlib
Project-URL: Issues, https://github.com/moltenform/shinerainsevenlib/issues
Classifier: Programming Language :: Python :: 3
Classifier: Operating System :: OS Independent
Requires-Python: >=3.8
License-File: LICENSE
Dynamic: license-file
